querybuilder_llm/__init__.py
querybuilder_llm/client.py
querybuilder_llm-0.2.0.dist-info/METADATA
querybuilder_llm-0.2.0.dist-info/WHEEL
querybuilder_llm-0.2.0.dist-info/top_level.txt
querybuilder_llm-0.2.0.dist-info/RECORD
