Metadata-Version: 2.4
Name: querybuilder-llm
Version: 0.2.0
Summary: A pip package to generate SQL/Mongo queries from natural language using an LLM API
Author: Manoj Shetty K
Requires-Python: >=3.8
Requires-Dist: requests
Dynamic: author
Dynamic: description
Dynamic: description-content-type
Dynamic: requires-dist
Dynamic: requires-python
Dynamic: summary
